{
  "posted": [
    {
      "id": "epl-061",
      "ig_media_id": "18029448581812737",
      "postedAt": "2026-05-16T06:12:22.194Z",
      "title": "【賽後回顧】阿斯頓維拉 4-2 利物浦：Watkins 梅開二度，維拉鎖定歐冠席位"
    },
    {
      "id": "epl-062",
      "ig_media_id": "18109519570926701",
      "postedAt": "2026-05-16T06:12:34.756Z",
      "title": "【賽前分析】兵工廠 vs 伯恩利：冠軍爭奪戰最終章，Arteta 能否在主場封王？"
    },
    {
      "id": "epl-063",
      "ig_media_id": "18322072138283607",
      "postedAt": "2026-05-16T06:12:49.343Z",
      "title": "【賽前分析】切爾西 vs 熱刺：倫敦德比生死戰，Spurs 的保級命運在此一搏"
    },
    {
      "id": "epl-065",
      "ig_media_id": "18425752642121255",
      "postedAt": "2026-05-16T23:11:48.207Z",
      "title": "【賽前分析】伯恩茅斯 vs 曼城：冠軍之路最後客場考驗，Haaland 能否射下爭冠關鍵三分？"
    },
    {
      "id": "epl-064",
      "ig_media_id": "17888699355508548",
      "postedAt": "2026-05-16T23:12:03.819Z",
      "title": "【賽後戰報】Villa 4-2 Liverpool：Watkins 梅開二度，維拉鎖定歐冠資格"
    }
  ]
}